AUTHORS.rst
CONTRIBUTING.rst
LICENSE
MANIFEST.in
README.rst
setup.cfg
setup.py
bin/fasta_length.py
bin/gsest.py
bin/kmer_hist.py
bin/read_sampler.py
bin/reads_size.py
c_src/covest_poissonmodule.c
covest/__init__.py
covest/constants.py
covest/covest.py
covest/data.py
covest/grid.py
covest/histogram.py
covest/inverse.py
covest/models.py
covest/perf.py
covest/utils.py
covest.egg-info/PKG-INFO
covest.egg-info/SOURCES.txt
covest.egg-info/dependency_links.txt
covest.egg-info/entry_points.txt
covest.egg-info/not-zip-safe
covest.egg-info/requires.txt
covest.egg-info/top_level.txt
docs/Makefile
docs/authors.rst
docs/conf.py
docs/contributing.rst
docs/index.rst
docs/make.bat
docs/readme.rst
tests/__init__.py
tests/test_data_manipulation.py
tests/test_histograms.py
tests/test_models.py
tests/data/empty.hist
tests/data/invalid.hist
tests/data/simulated_c10_e0.05_r100_k21.hist
tests/data/simulated_c10_e0.05_r100_k21_sparse.hist
tests/data/simulated_c10_e0_r100_k21.hist