Metadata-Version: 1.1
Name: covest
Version: 0.5.2
Summary: Covest estimates the coverage and genome size, just from k-mer abundance histogram computed from DNA sequences reads.
Home-page: https://github.com/mhozza/covest
Author: Michal Hozza
Author-email: mhozza@gmail.com
License: GNU GPLv3
Keywords: covest
Platform: UNKNOWN
Classifier: Development Status :: 2 - Pre-Alpha
Classifier: Intended Audience :: Science/Research
Classifier: License :: OSI Approved :: GNU General Public License v3 (GPLv3)
Classifier: Natural Language :: English
Classifier: Programming Language :: Python :: 3
Classifier: Programming Language :: Python :: 3.4
Classifier: Programming Language :: Python :: 3.5
Classifier: Topic :: Scientific/Engineering :: Bio-Informatics
